<annotation>
	<folder>images</folder>
	<filename>11.jpeg</filename>
	<path>E:\Desktop\summer stuff\images\11.jpeg</path>
	<source>
		<database>Unknown</database>
	</source>
	<size>
		<width>200</width>
		<height>60</height>
		<depth>3</depth>
	</size>
	<segmented>0</segmented>
	<object>
		<name>f</name>
		<pose>Unspecified</pose>
		<truncated>0</truncated>
		<difficult>0</difficult>
		<bndbox>
			<xmin>6</xmin>
			<ymin>4</ymin>
			<xmax>26</xmax>
			<ymax>37</ymax>
		</bndbox>
	</object>
	<object>
		<name>p</name>
		<pose>Unspecified</pose>
		<truncated>0</truncated>
		<difficult>0</difficult>
		<bndbox>
			<xmin>46</xmin>
			<ymin>13</ymin>
			<xmax>79</xmax>
			<ymax>42</ymax>
		</bndbox>
	</object>
	<object>
		<name>o</name>
		<pose>Unspecified</pose>
		<truncated>0</truncated>
		<difficult>0</difficult>
		<bndbox>
			<xmin>90</xmin>
			<ymin>18</ymin>
			<xmax>111</xmax>
			<ymax>39</ymax>
		</bndbox>
	</object>
	<object>
		<name>N</name>
		<pose>Unspecified</pose>
		<truncated>1</truncated>
		<difficult>0</difficult>
		<bndbox>
			<xmin>127</xmin>
			<ymin>1</ymin>
			<xmax>161</xmax>
			<ymax>34</ymax>
		</bndbox>
	</object>
	<object>
		<name>L</name>
		<pose>Unspecified</pose>
		<truncated>0</truncated>
		<difficult>0</difficult>
		<bndbox>
			<xmin>175</xmin>
			<ymin>13</ymin>
			<xmax>195</xmax>
			<ymax>41</ymax>
		</bndbox>
	</object>
</annotation>
